mypackage/__init__.py
mypackage/mymodule.py
tests/__init__.py
tests/tests_mymodule.py
jseok_mypackage-0.1.0.dist-info/METADATA
jseok_mypackage-0.1.0.dist-info/WHEEL
jseok_mypackage-0.1.0.dist-info/top_level.txt
jseok_mypackage-0.1.0.dist-info/RECORD
