Metadata-Version: 2.1
Name: jseok-mypackage
Version: 0.1.0
Summary: A simple example package
Home-page: https://github.com/koesnuj/python_study
Author: julim
Author-email: whizkid00@gmail.com
License: UNKNOWN
Platform: UNKNOWN
Classifier: Programming Language :: Python :: 3
Classifier: License :: OSI Approved :: MIT License
Classifier: Operating System :: OS Independent
Requires-Python: >=3.6
